aiorezka/__future.py
aiorezka/__init__.py
aiorezka/__main__.py
aiorezka/api.py
aiorezka/attributes.py
aiorezka/backend/__init__.py
aiorezka/backend/downloader.py
aiorezka/backend/movie.py
aiorezka/backend/movie_detail.py
aiorezka/backend/stream.py
aiorezka/cache.py
aiorezka/cli.py
aiorezka/enums.py
aiorezka/factories.py
aiorezka/logger.py
aiorezka/schemas.py
aiorezka/utils.py
aiorezka-1.3.1.dist-info/METADATA
aiorezka-1.3.1.dist-info/WHEEL
aiorezka-1.3.1.dist-info/RECORD
