Metadata-Version: 2.3
Name: aiorezka
Version: 1.3.1
Summary: 
Author: iYasha
Author-email: 33287747+iYasha@users.noreply.github.com
Requires-Python: >=3.9,<4.0
Classifier: Programming Language :: Python :: 3
Classifier: Programming Language :: Python :: 3.9
Classifier: Programming Language :: Python :: 3.10
Classifier: Programming Language :: Python :: 3.11
Classifier: Programming Language :: Python :: 3.12
Classifier: Programming Language :: Python :: 3.13
Provides-Extra: downloader
Requires-Dist: aiofiles (>=23.2.1,<24.0.0)
Requires-Dist: aiohttp (>=3.9.1,<4.0.0)
Requires-Dist: beautifulsoup4 (>=4.11.1,<5.0.0)
Requires-Dist: faker (>=21.0.0,<22.0.0)
Requires-Dist: pydantic (>=2.5.3,<3.0.0)
Requires-Dist: yt-dlp[aria2c] (>=2025.7.21,<2026.0.0) ; extra == "downloader"
